odoo/addons/account_reconcile_reconciliation_date/README.rst
odoo/addons/account_reconcile_reconciliation_date/__init__.py
odoo/addons/account_reconcile_reconciliation_date/__manifest__.py
odoo/addons/account_reconcile_reconciliation_date/i18n/account_reconcile_reconciliation_date.pot
odoo/addons/account_reconcile_reconciliation_date/i18n/es.po
odoo/addons/account_reconcile_reconciliation_date/i18n/es_AR.po
odoo/addons/account_reconcile_reconciliation_date/i18n/it.po
odoo/addons/account_reconcile_reconciliation_date/i18n/sv.po
odoo/addons/account_reconcile_reconciliation_date/i18n/zh_CN.po
odoo/addons/account_reconcile_reconciliation_date/models/__init__.py
odoo/addons/account_reconcile_reconciliation_date/models/account_full_reconcile.py
odoo/addons/account_reconcile_reconciliation_date/models/account_move.py
odoo/addons/account_reconcile_reconciliation_date/models/account_payment.py
odoo/addons/account_reconcile_reconciliation_date/readme/CONTRIBUTORS.rst
odoo/addons/account_reconcile_reconciliation_date/readme/DESCRIPTION.rst
odoo/addons/account_reconcile_reconciliation_date/static/description/icon.png
odoo/addons/account_reconcile_reconciliation_date/static/description/index.html
odoo/addons/account_reconcile_reconciliation_date/tests/__init__.py
odoo/addons/account_reconcile_reconciliation_date/tests/test_account_reconcile_reconciliation_date.py
odoo/addons/account_reconcile_reconciliation_date/views/account_move.xml
odoo/addons/account_reconcile_reconciliation_date/views/account_payment.xml
odoo14_addon_account_reconcile_reconciliation_date-14.0.1.0.1.dist-info/METADATA
odoo14_addon_account_reconcile_reconciliation_date-14.0.1.0.1.dist-info/WHEEL
odoo14_addon_account_reconcile_reconciliation_date-14.0.1.0.1.dist-info/top_level.txt
odoo14_addon_account_reconcile_reconciliation_date-14.0.1.0.1.dist-info/RECORD
